coinex/__init__.py
coinex/client.py
coinex_python-0.1.0.data/data/base.txt
coinex_python-0.1.0.dist-info/METADATA
coinex_python-0.1.0.dist-info/WHEEL
coinex_python-0.1.0.dist-info/top_level.txt
coinex_python-0.1.0.dist-info/RECORD
